cipherme/__init__.py
cipherme/affine_cipher.py
cipherme/caesar_cipher.py
cipherme/utils/__init__.py
cipherme/utils/number_operations.py
cipherme-0.1.4.dist-info/LICENSE
cipherme-0.1.4.dist-info/METADATA
cipherme-0.1.4.dist-info/WHEEL
cipherme-0.1.4.dist-info/top_level.txt
cipherme-0.1.4.dist-info/RECORD
