Metadata-Version: 2.1
Name: cipherme
Version: 0.1.4
Summary: Cipherme is a package that enables you to have fun with the common ciphers such as the Affine Cipher and Caesar Cipher.
Home-page: https://github.com/KelynPNjeri/Encrypto.git
Author: Kelyn Paul Njeri
Author-email: kelynpaul.devtopia@gmail.com
License: UNKNOWN
Platform: UNKNOWN
Classifier: Programming Language :: Python :: 3
Classifier: License :: OSI Approved :: MIT License
Classifier: Operating System :: OS Independent
